fluidlearn/__init__.py
fluidlearn/dataprocess.py
fluidlearn/fluidlearn.py
fluidlearn/fluidmodels.py
fluidlearn/losses.py
fluidlearn-0.2.0.dist-info/LICENSE.txt
fluidlearn-0.2.0.dist-info/METADATA
fluidlearn-0.2.0.dist-info/WHEEL
fluidlearn-0.2.0.dist-info/top_level.txt
fluidlearn-0.2.0.dist-info/RECORD
