Metadata-Version: 2.1
Name: fluidlearn
Version: 0.2.0
Summary: Package to solve fluid flow PDEs using deep learning
Home-page: https://github.com/mjayadharan/FluidLearn/archive/v0.2.0.tar.gz
Author: Manu Jayadharan
Author-email: manu.jayadharan@pitt.edu
License: UNKNOWN
Platform: UNKNOWN
Classifier: Programming Language :: Python :: 3
Classifier: License :: OSI Approved :: MIT License
Classifier: Operating System :: OS Independent
Requires-Python: >=3.6
